metaworkflows/__init__.py
metaworkflows/constants.py
metaworkflows/main.py
metaworkflows/utils.py
metaworkflows/core/__init__.py
metaworkflows/core/connections.py
metaworkflows/core/job.py
metaworkflows/core/pipeline.py
metaworkflows/engines/__init__.py
metaworkflows/engines/base.py
metaworkflows/engines/bash_engine.py
metaworkflows/engines/flink_engine.py
metaworkflows/engines/python_engine.py
metaworkflows/engines/spark_engine.py
metaworkflows/io/__init__.py
metaworkflows/io/base.py
metaworkflows/io/database.py
metaworkflows/io/file.py
metaworkflows/io/gcp_object_storage.py
metaworkflows/io/object_storage.py
metaworkflows/io/postgres_database.py
metaworkflows/transformers/__init__.py
metaworkflows/transformers/base.py
metaworkflows/transformers/sql.py
metaworkflows-0.2.2.dist-info/licenses/LICENSE
metaworkflows-0.2.2.dist-info/METADATA
metaworkflows-0.2.2.dist-info/WHEEL
metaworkflows-0.2.2.dist-info/entry_points.txt
metaworkflows-0.2.2.dist-info/top_level.txt
metaworkflows-0.2.2.dist-info/RECORD
