Metadata-Version: 2.4
Name: metaworkflows
Version: 0.2.2
Summary: A metadata-driven ETL framework
Author: tuanlxa, kiendt
Author-email: atuabk58@mbbank.com.vn
Classifier: Programming Language :: Python :: 3
Classifier: License :: OSI Approved :: MIT License
Classifier: Operating System :: OS Independent
Classifier: Development Status :: 3 - Alpha
Classifier: Intended Audience :: Developers
Requires-Python: >=3.10
License-File: LICENSE
Requires-Dist: PyYAML>=6.0
Requires-Dist: pandas>=1.0.0
Requires-Dist: sqlalchemy>=1.4.0
Requires-Dist: jsonschema==4.23.0
Provides-Extra: spark
Requires-Dist: pyspark>=3.0.0; extra == "spark"
Provides-Extra: postgres
Requires-Dist: psycopg2-binary>=2.9.0; extra == "postgres"
Provides-Extra: gcp
Requires-Dist: google-cloud-storage>=2.0.0; extra == "gcp"
Requires-Dist: google-cloud-secret-manager==2.23.0; extra == "gcp"
Requires-Dist: pyarrow>=1.0.0; extra == "gcp"
Dynamic: author
Dynamic: author-email
Dynamic: classifier
Dynamic: description
Dynamic: description-content-type
Dynamic: license-file
Dynamic: provides-extra
Dynamic: requires-dist
Dynamic: requires-python
Dynamic: summary
